MANIFEST.in
README.rst
requirements.txt
setup.cfg
setup.py
bootmachine/__init__.py
bootmachine/core.py
bootmachine/fabfile_dist.py
bootmachine/known_hosts.py
bootmachine/settings_dist.py
bootmachine/settings_tests.py
bootmachine/settings_validator.py
bootmachine.egg-info/PKG-INFO
bootmachine.egg-info/SOURCES.txt
bootmachine.egg-info/dependency_links.txt
bootmachine.egg-info/entry_points.txt
bootmachine.egg-info/not-zip-safe
bootmachine.egg-info/requires.txt
bootmachine.egg-info/top_level.txt
bootmachine/configuration/salt/pillars/bootmachine.sls
bootmachine/configuration/salt/pillars/bootmachine.sls.j2
bootmachine/configuration/salt/pillars/deploymachine.sls
bootmachine/configuration/salt/pillars/top.sls
bootmachine/configuration/salt/states/top.sls
bootmachine/configuration/salt/states/edit/emacs-nox.sls
bootmachine/configuration/salt/states/edit/vim.sls
bootmachine/configuration/salt/states/edit/vimrc
bootmachine/configuration/salt/states/edit/zile.sls
bootmachine/configuration/salt/states/groups/init.sls
bootmachine/configuration/salt/states/iptables/init.sls
bootmachine/configuration/salt/states/iptables/iptables
bootmachine/configuration/salt/states/iptables/rules.j2
bootmachine/configuration/salt/states/kernel/lts.sls
bootmachine/configuration/salt/states/netcfg/init.sls
bootmachine/configuration/salt/states/netcfg/netcfg.conf.j2
bootmachine/configuration/salt/states/ntp/init.sls
bootmachine/configuration/salt/states/pacman/init.sls
bootmachine/configuration/salt/states/pacman/mirrorlist.uk
bootmachine/configuration/salt/states/pacman/mirrorlist.usa
bootmachine/configuration/salt/states/pacman/pacman.conf.j2
bootmachine/configuration/salt/states/pacman/uk.sls
bootmachine/configuration/salt/states/pacman/usa.sls
bootmachine/configuration/salt/states/salt/dirs.sls
bootmachine/configuration/salt/states/salt/init.sls
bootmachine/configuration/salt/states/salt/master.config.j2
bootmachine/configuration/salt/states/salt/master.sls
bootmachine/configuration/salt/states/salt/minion.config.j2
bootmachine/configuration/salt/states/ssh/init.sls
bootmachine/configuration/salt/states/ssh/sshd_config.j2
bootmachine/configuration/salt/states/sudo/init.sls
bootmachine/configuration/salt/states/sudo/sudoers
