Metadata-Version: 1.1
Name: bootmachine
Version: 0.6.0
Summary: A fabric library to bootstrap servers and configuration management software.
Home-page: http://bootmachine.readthedocs.org/
Author: Thomas Schreiber
Author-email: tom@nillab.com
License: BSD
Platform: UNKNOWN
Classifier: Development Status :: 3 - Alpha
Classifier: Intended Audience :: Developers
Classifier: License :: OSI Approved :: BSD License
Classifier: Operating System :: OS Independent
Classifier: Programming Language :: Python
Classifier: Topic :: Software Development :: Libraries :: Python Modules
